jayspytools/__init__.py
jayspytools-0.1.2.dist-info/WHEEL
jayspytools-0.1.2.dist-info/METADATA
jayspytools-0.1.2.dist-info/RECORD
