Metadata-Version: 2.1
Name: jayspytools
Version: 0.1.2
Summary: 
Author: jaygovind-sahu
Author-email: jaygovind.sahu@yahoo.com
Requires-Python: >=3.9,<4.0
Classifier: Programming Language :: Python :: 3
Classifier: Programming Language :: Python :: 3.10
Classifier: Programming Language :: Python :: 3.9
Requires-Dist: pyspark (>=3.2.1,<4.0.0)
